Metadata-Version: 2.1
Name: mxr-bigdata
Version: 2.1.0
Summary: 这是一个只有两个变量的包
Home-page: UNKNOWN
Author: 大数据1
Author-email: 1280184739@qq.com
License: UNKNOWN
Platform: UNKNOWN
